{
  	"Character01": 
    [
    	{"ID":"1001","Name":"强力击","ParentID":["-1"],"Pos":[-5,0],"Info":"使用鸽子对敌方造成强力打击"},
    	{"ID":"1002","Name":"强力击击","ParentID":["1001"],"Pos":[-3,2],"Info":"使用鸽子王对敌方造成强力打击"},
    	{"ID":"1003","Name":"真银斩","ParentID":["1001"],"Pos":[-3,-2],"Info":"将鸽子拿在手上发出斩击，看上去是银色的"},
        {"ID":"1004","Name":"强力击击击","ParentID":["1002"],"Pos":[-1,2],"Info":"使用鸽子皇对敌方造成强力打击"},
    	{"ID":"1005","Name":"真·真银斩","ParentID":["1003"],"Pos":[-3,-4],"Info":"一手一只鸽子发出双手大范围斩击，看上去是银色的"},
        {"ID":"1006","Name":"强力连击","ParentID":["1003","1004"],"Pos":[1,0],"Info":"使用鸽子一家对敌方造成强力打击"}
  	]
}